mailspoof/__init__.py
mailspoof/__main__.py
mailspoof/issues.py
mailspoof/scanners.py
mailspoof-0.1.1.dist-info/entry_points.txt
mailspoof-0.1.1.dist-info/LICENSE
mailspoof-0.1.1.dist-info/WHEEL
mailspoof-0.1.1.dist-info/METADATA
mailspoof-0.1.1.dist-info/RECORD
